gamma/__init__.py
gamma/_base.py
gamma/_bayesian_mixture.py
gamma/_gaussian_mixture.py
gamma/seismic_ops.py
gamma/utils.py
gmma-1.2.12.dist-info/LICENSE
gmma-1.2.12.dist-info/METADATA
gmma-1.2.12.dist-info/WHEEL
gmma-1.2.12.dist-info/top_level.txt
gmma-1.2.12.dist-info/RECORD
