Metadata-Version: 2.1
Name: GMMA
Version: 1.2.12
License-File: LICENSE
Requires-Dist: scikit-learn
Requires-Dist: scipy
Requires-Dist: numpy
Requires-Dist: pyproj
Requires-Dist: tqdm
Requires-Dist: numba
